celery_worker/__init__.py
celery_worker-0.0.6.dist-info/METADATA
celery_worker-0.0.6.dist-info/RECORD
celery_worker-0.0.6.dist-info/WHEEL
celery_worker-0.0.6.dist-info/top_level.txt
