Metadata-Version: 2.1
Name: celery-worker
Version: 0.0.6
Summary: A Simple celery worker
Home-page: https://github.com/anthonykgross/celery-worker
Author: Anthony K GROSS
Author-email: anthony.k.gross@gmail.com
License: UNKNOWN
Platform: UNKNOWN
Classifier: Programming Language :: Python :: 3
Classifier: License :: OSI Approved :: MIT License
Classifier: Operating System :: OS Independent
Requires-Python: >=3.6
Requires-Dist: celery (==4.4.5)
